{
  "image_path": "data\\raw_images\\orthophotos\\DJI_0511.tif",
  "annotations": [
    {
      "type": "polygon",
      "class": "commercial",
      "confidence": 1.0,
      "raw_points": [
        [
          483,
          243
        ],
        [
          490,
          251
        ],
        [
          515,
          291
        ],
        [
          526,
          328
        ],
        [
          536,
          358
        ],
        [
          545,
          371
        ],
        [
          548,
          378
        ],
        [
          550,
          391
        ],
        [
          556,
          400
        ],
        [
          556,
          408
        ],
        [
          563,
          416
        ],
        [
          570,
          428
        ],
        [
          576,
          435
        ],
        [
          583,
          441
        ],
        [
          606,
          445
        ],
        [
          635,
          438
        ],
        [
          675,
          420
        ],
        [
          710,
          410
        ],
        [
          745,
          393
        ],
        [
          763,
          385
        ],
        [
          770,
          380
        ],
        [
          800,
          365
        ],
        [
          816,
          356
        ],
        [
          831,
          343
        ],
        [
          838,
          338
        ],
        [
          841,
          333
        ],
        [
          846,
          330
        ],
        [
          850,
          325
        ],
        [
          853,
          320
        ],
        [
          856,
          313
        ],
        [
          838,
          271
        ],
        [
          823,
          231
        ],
        [
          820,
          225
        ],
        [
          808,
          176
        ],
        [
          803,
          153
        ],
        [
          800,
          146
        ],
        [
          791,
          143
        ],
        [
          781,
          138
        ],
        [
          770,
          133
        ],
        [
          761,
          126
        ],
        [
          756,
          125
        ],
        [
          755,
          120
        ],
        [
          750,
          115
        ],
        [
          746,
          111
        ],
        [
          740,
          108
        ],
        [
          735,
          106
        ],
        [
          728,
          106
        ],
        [
          715,
          113
        ],
        [
          710,
          115
        ]
      ],
      "processed_points": [
        [
          483,
          243
        ],
        [
          490,
          251
        ],
        [
          515,
          291
        ],
        [
          526,
          328
        ],
        [
          536,
          358
        ],
        [
          545,
          371
        ],
        [
          550,
          391
        ],
        [
          556,
          400
        ],
        [
          556,
          408
        ],
        [
          563,
          416
        ],
        [
          570,
          428
        ],
        [
          576,
          435
        ],
        [
          583,
          441
        ],
        [
          606,
          445
        ],
        [
          635,
          438
        ],
        [
          675,
          420
        ],
        [
          710,
          410
        ],
        [
          745,
          393
        ],
        [
          763,
          385
        ],
        [
          770,
          380
        ],
        [
          800,
          365
        ],
        [
          816,
          356
        ],
        [
          831,
          343
        ],
        [
          838,
          338
        ],
        [
          846,
          330
        ],
        [
          853,
          320
        ],
        [
          838,
          271
        ],
        [
          823,
          231
        ],
        [
          808,
          176
        ],
        [
          803,
          153
        ],
        [
          791,
          143
        ],
        [
          781,
          138
        ],
        [
          770,
          133
        ],
        [
          761,
          126
        ],
        [
          755,
          120
        ],
        [
          746,
          111
        ],
        [
          735,
          106
        ],
        [
          715,
          113
        ]
      ],
      "completed_points": [
        [
          483,
          243
        ],
        [
          715,
          113
        ],
        [
          735,
          106
        ],
        [
          746,
          111
        ],
        [
          791,
          143
        ],
        [
          803,
          153
        ],
        [
          853,
          320
        ],
        [
          846,
          330
        ],
        [
          838,
          338
        ],
        [
          816,
          356
        ],
        [
          800,
          365
        ],
        [
          763,
          385
        ],
        [
          710,
          410
        ],
        [
          635,
          438
        ],
        [
          606,
          445
        ],
        [
          583,
          441
        ],
        [
          576,
          435
        ],
        [
          570,
          428
        ],
        [
          556,
          408
        ]
      ],
      "points": [
        [
          483,
          243
        ],
        [
          715,
          113
        ],
        [
          735,
          106
        ],
        [
          746,
          111
        ],
        [
          791,
          143
        ],
        [
          803,
          153
        ],
        [
          853,
          320
        ],
        [
          846,
          330
        ],
        [
          838,
          338
        ],
        [
          816,
          356
        ],
        [
          800,
          365
        ],
        [
          763,
          385
        ],
        [
          710,
          410
        ],
        [
          635,
          438
        ],
        [
          606,
          445
        ],
        [
          583,
          441
        ],
        [
          576,
          435
        ],
        [
          570,
          428
        ],
        [
          556,
          408
        ]
      ],
      "pixel_coordinates": [
        [
          483,
          243
        ],
        [
          715,
          113
        ],
        [
          735,
          106
        ],
        [
          746,
          111
        ],
        [
          791,
          143
        ],
        [
          803,
          153
        ],
        [
          853,
          320
        ],
        [
          846,
          330
        ],
        [
          838,
          338
        ],
        [
          816,
          356
        ],
        [
          800,
          365
        ],
        [
          763,
          385
        ],
        [
          710,
          410
        ],
        [
          635,
          438
        ],
        [
          606,
          445
        ],
        [
          583,
          441
        ],
        [
          576,
          435
        ],
        [
          570,
          428
        ],
        [
          556,
          408
        ]
      ],
      "geographic_coordinates": [
        [
          4.512672469890376,
          7.5170101184577405
        ],
        [
          4.5127138702903755,
          7.51703327002774
        ],
        [
          4.512717439290376,
          7.517034516650741
        ],
        [
          4.512719402240376,
          7.51703362620574
        ],
        [
          4.512727432490376,
          7.5170279273577405
        ],
        [
          4.512729573890375,
          7.517026146467741
        ],
        [
          4.512738496390376,
          7.516996405604741
        ],
        [
          4.512737247240375,
          7.516994624714741
        ],
        [
          4.512735819640375,
          7.51699320000274
        ],
        [
          4.5127318937403755,
          7.51698999440074
        ],
        [
          4.5127290385403755,
          7.516988391599741
        ],
        [
          4.5127224358903755,
          7.516984829819741
        ],
        [
          4.512712978040375,
          7.516980377594741
        ],
        [
          4.512699594290376,
          7.516975391102741
        ],
        [
          4.5126944192403755,
          7.51697414447974
        ],
        [
          4.512690314890375,
          7.51697485683574
        ],
        [
          4.512689065740376,
          7.51697592536974
        ],
        [
          4.512687995040376,
          7.516977171992741
        ],
        [
          4.512685496740375,
          7.516980733772741
        ]
      ],
      "center_lon": 4.512712367553534,
      "center_lat": 7.51699745539253
    },
    {
      "type": "polygon",
      "class": "commercial",
      "confidence": 1.0,
      "raw_points": [
        [
          970,
          1025
        ],
        [
          973,
          1030
        ],
        [
          981,
          1038
        ],
        [
          1011,
          1078
        ],
        [
          1031,
          1103
        ],
        [
          1041,
          1111
        ],
        [
          1041,
          1118
        ],
        [
          1051,
          1151
        ],
        [
          1058,
          1168
        ],
        [
          1068,
          1190
        ],
        [
          1073,
          1200
        ],
        [
          1083,
          1211
        ],
        [
          1101,
          1231
        ],
        [
          1115,
          1255
        ],
        [
          1121,
          1265
        ],
        [
          1126,
          1276
        ],
        [
          1138,
          1320
        ],
        [
          1145,
          1338
        ],
        [
          1150,
          1351
        ],
        [
          1160,
          1365
        ],
        [
          1168,
          1375
        ],
        [
          1173,
          1381
        ],
        [
          1180,
          1393
        ],
        [
          1181,
          1398
        ],
        [
          1183,
          1403
        ],
        [
          1188,
          1413
        ],
        [
          1191,
          1425
        ],
        [
          1196,
          1440
        ],
        [
          1211,
          1468
        ],
        [
          1220,
          1478
        ],
        [
          1221,
          1483
        ],
        [
          1228,
          1485
        ],
        [
          1235,
          1481
        ],
        [
          1248,
          1471
        ],
        [
          1276,
          1458
        ],
        [
          1306,
          1446
        ],
        [
          1333,
          1436
        ],
        [
          1350,
          1430
        ],
        [
          1356,
          1428
        ],
        [
          1386,
          1425
        ],
        [
          1406,
          1418
        ],
        [
          1426,
          1411
        ],
        [
          1438,
          1403
        ],
        [
          1445,
          1396
        ],
        [
          1448,
          1390
        ],
        [
          1451,
          1385
        ],
        [
          1450,
          1376
        ],
        [
          1416,
          1311
        ],
        [
          1393,
          1270
        ],
        [
          1381,
          1251
        ],
        [
          1373,
          1228
        ],
        [
          1370,
          1223
        ],
        [
          1348,
          1188
        ],
        [
          1328,
          1156
        ],
        [
          1301,
          1105
        ],
        [
          1298,
          1085
        ],
        [
          1296,
          1080
        ],
        [
          1275,
          1036
        ],
        [
          1258,
          1005
        ],
        [
          1248,
          985
        ],
        [
          1235,
          971
        ],
        [
          1228,
          965
        ],
        [
          1225,
          958
        ],
        [
          1203,
          933
        ],
        [
          1191,
          918
        ],
        [
          1188,
          923
        ],
        [
          1190,
          931
        ],
        [
          1200,
          936
        ],
        [
          1201,
          941
        ],
        [
          1195,
          941
        ],
        [
          1190,
          938
        ],
        [
          1181,
          938
        ],
        [
          1175,
          938
        ],
        [
          1161,
          941
        ],
        [
          1143,
          951
        ],
        [
          1128,
          960
        ],
        [
          1115,
          971
        ],
        [
          1096,
          978
        ],
        [
          1078,
          985
        ],
        [
          1065,
          990
        ],
        [
          1053,
          991
        ],
        [
          1045,
          995
        ],
        [
          1035,
          1000
        ],
        [
          1023,
          1003
        ],
        [
          1015,
          1006
        ],
        [
          1001,
          1011
        ],
        [
          988,
          1018
        ]
      ],
      "processed_points": [
        [
          970,
          1025
        ],
        [
          981,
          1038
        ],
        [
          1011,
          1078
        ],
        [
          1031,
          1103
        ],
        [
          1041,
          1111
        ],
        [
          1051,
          1151
        ],
        [
          1058,
          1168
        ],
        [
          1068,
          1190
        ],
        [
          1073,
          1200
        ],
        [
          1083,
          1211
        ],
        [
          1101,
          1231
        ],
        [
          1115,
          1255
        ],
        [
          1121,
          1265
        ],
        [
          1126,
          1276
        ],
        [
          1138,
          1320
        ],
        [
          1145,
          1338
        ],
        [
          1150,
          1351
        ],
        [
          1160,
          1365
        ],
        [
          1168,
          1375
        ],
        [
          1180,
          1393
        ],
        [
          1183,
          1403
        ],
        [
          1188,
          1413
        ],
        [
          1191,
          1425
        ],
        [
          1196,
          1440
        ],
        [
          1211,
          1468
        ],
        [
          1220,
          1478
        ],
        [
          1228,
          1485
        ],
        [
          1235,
          1481
        ],
        [
          1248,
          1471
        ],
        [
          1276,
          1458
        ],
        [
          1306,
          1446
        ],
        [
          1333,
          1436
        ],
        [
          1350,
          1430
        ],
        [
          1386,
          1425
        ],
        [
          1406,
          1418
        ],
        [
          1426,
          1411
        ],
        [
          1438,
          1403
        ],
        [
          1445,
          1396
        ],
        [
          1451,
          1385
        ],
        [
          1450,
          1376
        ],
        [
          1416,
          1311
        ],
        [
          1393,
          1270
        ],
        [
          1381,
          1251
        ],
        [
          1373,
          1228
        ],
        [
          1348,
          1188
        ],
        [
          1328,
          1156
        ],
        [
          1301,
          1105
        ],
        [
          1298,
          1085
        ],
        [
          1275,
          1036
        ],
        [
          1258,
          1005
        ],
        [
          1248,
          985
        ],
        [
          1235,
          971
        ],
        [
          1228,
          965
        ],
        [
          1203,
          933
        ],
        [
          1191,
          918
        ],
        [
          1190,
          931
        ],
        [
          1201,
          941
        ],
        [
          1181,
          938
        ],
        [
          1161,
          941
        ],
        [
          1143,
          951
        ],
        [
          1128,
          960
        ],
        [
          1115,
          971
        ],
        [
          1096,
          978
        ],
        [
          1078,
          985
        ],
        [
          1065,
          990
        ],
        [
          1053,
          991
        ],
        [
          1045,
          995
        ],
        [
          1035,
          1000
        ],
        [
          1023,
          1003
        ],
        [
          1015,
          1006
        ],
        [
          1001,
          1011
        ],
        [
          988,
          1018
        ]
      ],
      "completed_points": [
        [
          970,
          1025
        ],
        [
          981,
          1038
        ],
        [
          1011,
          1078
        ],
        [
          1031,
          1103
        ],
        [
          1041,
          1111
        ],
        [
          1051,
          1151
        ],
        [
          1058,
          1168
        ],
        [
          1068,
          1190
        ],
        [
          1073,
          1200
        ],
        [
          1083,
          1211
        ],
        [
          1101,
          1231
        ],
        [
          1115,
          1255
        ],
        [
          1121,
          1265
        ],
        [
          1126,
          1276
        ],
        [
          1138,
          1320
        ],
        [
          1145,
          1338
        ],
        [
          1150,
          1351
        ],
        [
          1160,
          1365
        ],
        [
          1168,
          1375
        ],
        [
          1180,
          1393
        ],
        [
          1183,
          1403
        ],
        [
          1188,
          1413
        ],
        [
          1191,
          1425
        ],
        [
          1196,
          1440
        ],
        [
          1211,
          1468
        ],
        [
          1220,
          1478
        ],
        [
          1228,
          1485
        ],
        [
          1235,
          1481
        ],
        [
          1248,
          1471
        ],
        [
          1276,
          1458
        ],
        [
          1306,
          1446
        ],
        [
          1333,
          1436
        ],
        [
          1350,
          1430
        ],
        [
          1386,
          1425
        ],
        [
          1406,
          1418
        ],
        [
          1426,
          1411
        ],
        [
          1438,
          1403
        ],
        [
          1445,
          1396
        ],
        [
          1451,
          1385
        ],
        [
          1450,
          1376
        ],
        [
          1416,
          1311
        ],
        [
          1393,
          1270
        ],
        [
          1381,
          1251
        ],
        [
          1373,
          1228
        ],
        [
          1348,
          1188
        ],
        [
          1328,
          1156
        ],
        [
          1301,
          1105
        ],
        [
          1298,
          1085
        ],
        [
          1275,
          1036
        ],
        [
          1258,
          1005
        ],
        [
          1248,
          985
        ],
        [
          1235,
          971
        ],
        [
          1228,
          965
        ],
        [
          1203,
          933
        ],
        [
          1191,
          918
        ],
        [
          1190,
          931
        ],
        [
          1201,
          941
        ],
        [
          1181,
          938
        ],
        [
          1161,
          941
        ],
        [
          1143,
          951
        ],
        [
          1128,
          960
        ],
        [
          1115,
          971
        ],
        [
          1096,
          978
        ],
        [
          1078,
          985
        ],
        [
          1065,
          990
        ],
        [
          1053,
          991
        ],
        [
          1045,
          995
        ],
        [
          1035,
          1000
        ],
        [
          1023,
          1003
        ],
        [
          1015,
          1006
        ],
        [
          1001,
          1011
        ],
        [
          988,
          1018
        ],
        [
          970,
          1025
        ]
      ],
      "points": [
        [
          970,
          1025
        ],
        [
          1191,
          918
        ],
        [
          1248,
          985
        ],
        [
          1275,
          1036
        ],
        [
          1450,
          1376
        ],
        [
          1451,
          1385
        ],
        [
          1445,
          1396
        ],
        [
          1438,
          1403
        ],
        [
          1426,
          1411
        ],
        [
          1228,
          1485
        ],
        [
          1220,
          1478
        ],
        [
          1211,
          1468
        ]
      ],
      "pixel_coordinates": [
        [
          970,
          1025
        ],
        [
          1191,
          918
        ],
        [
          1248,
          985
        ],
        [
          1275,
          1036
        ],
        [
          1450,
          1376
        ],
        [
          1451,
          1385
        ],
        [
          1445,
          1396
        ],
        [
          1438,
          1403
        ],
        [
          1426,
          1411
        ],
        [
          1228,
          1485
        ],
        [
          1220,
          1478
        ],
        [
          1211,
          1468
        ]
      ],
      "geographic_coordinates": [
        [
          4.512759375040376,
          7.51687085285974
        ],
        [
          4.5127988124903755,
          7.5168899083827405
        ],
        [
          4.512808984140376,
          7.516877976419741
        ],
        [
          4.512813802290376,
          7.516868893880741
        ],
        [
          4.512845031040376,
          7.51680834362074
        ],
        [
          4.512845209490376,
          7.5168067408197405
        ],
        [
          4.512844138790376,
          7.51680478184074
        ],
        [
          4.512842889640376,
          7.516803535217741
        ],
        [
          4.512840748240376,
          7.516802110505741
        ],
        [
          4.512805415140376,
          7.5167889319197405
        ],
        [
          4.512803987540376,
          7.51679017854274
        ],
        [
          4.512802381490376,
          7.516791959432741
        ]
      ],
      "center_lon": 4.5128175646112085,
      "center_lat": 7.5168253511202385
    },
    {
      "type": "polygon",
      "class": "commercial",
      "confidence": 1.0,
      "raw_points": [
        [
          780,
          1133
        ],
        [
          783,
          1140
        ],
        [
          813,
          1180
        ],
        [
          823,
          1205
        ],
        [
          826,
          1211
        ],
        [
          826,
          1220
        ],
        [
          828,
          1236
        ],
        [
          828,
          1253
        ],
        [
          828,
          1261
        ],
        [
          828,
          1270
        ],
        [
          828,
          1278
        ],
        [
          835,
          1303
        ],
        [
          848,
          1331
        ],
        [
          865,
          1353
        ],
        [
          875,
          1358
        ],
        [
          875,
          1365
        ],
        [
          876,
          1371
        ],
        [
          878,
          1381
        ],
        [
          886,
          1391
        ],
        [
          895,
          1400
        ],
        [
          915,
          1431
        ],
        [
          920,
          1443
        ],
        [
          921,
          1448
        ],
        [
          926,
          1460
        ],
        [
          933,
          1478
        ],
        [
          935,
          1486
        ],
        [
          941,
          1496
        ],
        [
          946,
          1503
        ],
        [
          953,
          1515
        ],
        [
          958,
          1525
        ],
        [
          973,
          1546
        ],
        [
          983,
          1565
        ],
        [
          988,
          1573
        ],
        [
          995,
          1581
        ],
        [
          1000,
          1586
        ],
        [
          1008,
          1591
        ],
        [
          1021,
          1591
        ],
        [
          1035,
          1591
        ],
        [
          1041,
          1588
        ],
        [
          1061,
          1581
        ],
        [
          1078,
          1573
        ],
        [
          1091,
          1565
        ],
        [
          1106,
          1555
        ],
        [
          1116,
          1551
        ],
        [
          1126,
          1545
        ],
        [
          1135,
          1541
        ],
        [
          1161,
          1525
        ],
        [
          1175,
          1515
        ],
        [
          1183,
          1510
        ],
        [
          1188,
          1508
        ],
        [
          1193,
          1505
        ],
        [
          1200,
          1505
        ],
        [
          1206,
          1505
        ],
        [
          1205,
          1493
        ],
        [
          1193,
          1458
        ],
        [
          1183,
          1445
        ],
        [
          1178,
          1440
        ],
        [
          1175,
          1433
        ],
        [
          1155,
          1400
        ],
        [
          1145,
          1381
        ],
        [
          1141,
          1371
        ],
        [
          1140,
          1363
        ],
        [
          1131,
          1345
        ],
        [
          1128,
          1340
        ],
        [
          1106,
          1296
        ],
        [
          1091,
          1266
        ],
        [
          1086,
          1261
        ],
        [
          1078,
          1250
        ],
        [
          1055,
          1211
        ],
        [
          1038,
          1171
        ],
        [
          1033,
          1156
        ],
        [
          1030,
          1145
        ],
        [
          1010,
          1093
        ],
        [
          1003,
          1075
        ],
        [
          1001,
          1070
        ],
        [
          995,
          1065
        ],
        [
          988,
          1051
        ],
        [
          986,
          1046
        ],
        [
          981,
          1041
        ],
        [
          975,
          1038
        ],
        [
          970,
          1035
        ]
      ],
      "processed_points": [
        [
          780,
          1133
        ],
        [
          813,
          1180
        ],
        [
          823,
          1205
        ],
        [
          826,
          1220
        ],
        [
          828,
          1236
        ],
        [
          828,
          1253
        ],
        [
          828,
          1261
        ],
        [
          828,
          1270
        ],
        [
          828,
          1278
        ],
        [
          835,
          1303
        ],
        [
          848,
          1331
        ],
        [
          865,
          1353
        ],
        [
          875,
          1358
        ],
        [
          876,
          1371
        ],
        [
          878,
          1381
        ],
        [
          886,
          1391
        ],
        [
          895,
          1400
        ],
        [
          915,
          1431
        ],
        [
          920,
          1443
        ],
        [
          926,
          1460
        ],
        [
          933,
          1478
        ],
        [
          935,
          1486
        ],
        [
          941,
          1496
        ],
        [
          946,
          1503
        ],
        [
          953,
          1515
        ],
        [
          958,
          1525
        ],
        [
          973,
          1546
        ],
        [
          983,
          1565
        ],
        [
          988,
          1573
        ],
        [
          995,
          1581
        ],
        [
          1008,
          1591
        ],
        [
          1021,
          1591
        ],
        [
          1035,
          1591
        ],
        [
          1061,
          1581
        ],
        [
          1078,
          1573
        ],
        [
          1091,
          1565
        ],
        [
          1106,
          1555
        ],
        [
          1116,
          1551
        ],
        [
          1126,
          1545
        ],
        [
          1135,
          1541
        ],
        [
          1161,
          1525
        ],
        [
          1175,
          1515
        ],
        [
          1183,
          1510
        ],
        [
          1193,
          1505
        ],
        [
          1206,
          1505
        ],
        [
          1205,
          1493
        ],
        [
          1193,
          1458
        ],
        [
          1183,
          1445
        ],
        [
          1175,
          1433
        ],
        [
          1155,
          1400
        ],
        [
          1145,
          1381
        ],
        [
          1141,
          1371
        ],
        [
          1140,
          1363
        ],
        [
          1131,
          1345
        ],
        [
          1106,
          1296
        ],
        [
          1091,
          1266
        ],
        [
          1078,
          1250
        ],
        [
          1055,
          1211
        ],
        [
          1038,
          1171
        ],
        [
          1033,
          1156
        ],
        [
          1030,
          1145
        ],
        [
          1010,
          1093
        ],
        [
          1003,
          1075
        ],
        [
          995,
          1065
        ],
        [
          988,
          1051
        ],
        [
          981,
          1041
        ],
        [
          970,
          1035
        ]
      ],
      "completed_points": [
        [
          780,
          1133
        ],
        [
          970,
          1035
        ],
        [
          981,
          1041
        ],
        [
          988,
          1051
        ],
        [
          1003,
          1075
        ],
        [
          1193,
          1458
        ],
        [
          1205,
          1493
        ],
        [
          1206,
          1505
        ],
        [
          1078,
          1573
        ],
        [
          1061,
          1581
        ],
        [
          1035,
          1591
        ],
        [
          1008,
          1591
        ],
        [
          995,
          1581
        ],
        [
          988,
          1573
        ],
        [
          958,
          1525
        ],
        [
          935,
          1486
        ],
        [
          848,
          1331
        ],
        [
          835,
          1303
        ]
      ],
      "points": [
        [
          780,
          1133
        ],
        [
          970,
          1035
        ],
        [
          981,
          1041
        ],
        [
          988,
          1051
        ],
        [
          1003,
          1075
        ],
        [
          1193,
          1458
        ],
        [
          1205,
          1493
        ],
        [
          1206,
          1505
        ],
        [
          1078,
          1573
        ],
        [
          1061,
          1581
        ],
        [
          1035,
          1591
        ],
        [
          1008,
          1591
        ],
        [
          995,
          1581
        ],
        [
          988,
          1573
        ],
        [
          958,
          1525
        ],
        [
          935,
          1486
        ],
        [
          848,
          1331
        ],
        [
          835,
          1303
        ]
      ],
      "pixel_coordinates": [
        [
          780,
          1133
        ],
        [
          970,
          1035
        ],
        [
          981,
          1041
        ],
        [
          988,
          1051
        ],
        [
          1003,
          1075
        ],
        [
          1193,
          1458
        ],
        [
          1205,
          1493
        ],
        [
          1206,
          1505
        ],
        [
          1078,
          1573
        ],
        [
          1061,
          1581
        ],
        [
          1035,
          1591
        ],
        [
          1008,
          1591
        ],
        [
          995,
          1581
        ],
        [
          988,
          1573
        ],
        [
          958,
          1525
        ],
        [
          935,
          1486
        ],
        [
          848,
          1331
        ],
        [
          835,
          1303
        ]
      ],
      "geographic_coordinates": [
        [
          4.512725469540376,
          7.51685161924774
        ],
        [
          4.512759375040376,
          7.51686907196974
        ],
        [
          4.5127613379903755,
          7.51686800343574
        ],
        [
          4.512762587140376,
          7.51686622254574
        ],
        [
          4.512765263890375,
          7.5168619484097405
        ],
        [
          4.512799169390376,
          7.516793740322741
        ],
        [
          4.512801310790375,
          7.516787507207741
        ],
        [
          4.512801489240376,
          7.516785370139741
        ],
        [
          4.512778647640376,
          7.51677326008774
        ],
        [
          4.512775613990375,
          7.5167718353757405
        ],
        [
          4.512770974290375,
          7.5167700544857405
        ],
        [
          4.512766156140375,
          7.5167700544857405
        ],
        [
          4.512763836290375,
          7.5167718353757405
        ],
        [
          4.512762587140376,
          7.51677326008774
        ],
        [
          4.512757233640375,
          7.516781808359741
        ],
        [
          4.512753129290376,
          7.51678875383074
        ],
        [
          4.5127376041403755,
          7.51681635762574
        ],
        [
          4.512735284290375,
          7.516821344117741
        ]
      ],
      "center_lon": 4.51276539277093,
      "center_lat": 7.516806780395074
    },
    {
      "type": "polygon",
      "class": "commercial",
      "confidence": 1.0,
      "raw_points": [
        [
          541,
          1256
        ],
        [
          541,
          1270
        ],
        [
          551,
          1315
        ],
        [
          568,
          1345
        ],
        [
          581,
          1378
        ],
        [
          593,
          1398
        ],
        [
          601,
          1420
        ],
        [
          603,
          1425
        ],
        [
          613,
          1438
        ],
        [
          618,
          1443
        ],
        [
          626,
          1451
        ],
        [
          631,
          1453
        ],
        [
          636,
          1456
        ],
        [
          651,
          1471
        ],
        [
          675,
          1511
        ],
        [
          683,
          1528
        ],
        [
          686,
          1536
        ],
        [
          700,
          1573
        ],
        [
          705,
          1581
        ],
        [
          711,
          1596
        ],
        [
          715,
          1605
        ],
        [
          718,
          1611
        ],
        [
          733,
          1633
        ],
        [
          741,
          1645
        ],
        [
          743,
          1651
        ],
        [
          746,
          1656
        ],
        [
          746,
          1663
        ],
        [
          755,
          1685
        ],
        [
          763,
          1695
        ],
        [
          768,
          1698
        ],
        [
          775,
          1698
        ],
        [
          781,
          1698
        ],
        [
          788,
          1698
        ],
        [
          796,
          1698
        ],
        [
          806,
          1696
        ],
        [
          816,
          1691
        ],
        [
          828,
          1685
        ],
        [
          838,
          1680
        ],
        [
          853,
          1671
        ],
        [
          863,
          1663
        ],
        [
          873,
          1658
        ],
        [
          883,
          1655
        ],
        [
          920,
          1641
        ],
        [
          945,
          1628
        ],
        [
          955,
          1621
        ],
        [
          960,
          1618
        ],
        [
          963,
          1613
        ],
        [
          966,
          1608
        ],
        [
          965,
          1588
        ],
        [
          963,
          1581
        ],
        [
          943,
          1543
        ],
        [
          923,
          1510
        ],
        [
          921,
          1498
        ],
        [
          915,
          1481
        ],
        [
          903,
          1451
        ],
        [
          890,
          1418
        ],
        [
          871,
          1386
        ],
        [
          861,
          1365
        ],
        [
          855,
          1345
        ],
        [
          853,
          1338
        ],
        [
          848,
          1333
        ],
        [
          830,
          1303
        ],
        [
          816,
          1271
        ],
        [
          810,
          1253
        ],
        [
          808,
          1243
        ],
        [
          801,
          1238
        ],
        [
          778,
          1215
        ],
        [
          763,
          1186
        ],
        [
          761,
          1170
        ],
        [
          761,
          1163
        ],
        [
          756,
          1158
        ],
        [
          753,
          1151
        ],
        [
          746,
          1141
        ],
        [
          745,
          1136
        ]
      ],
      "processed_points": [
        [
          541,
          1256
        ],
        [
          541,
          1270
        ],
        [
          551,
          1315
        ],
        [
          568,
          1345
        ],
        [
          581,
          1378
        ],
        [
          593,
          1398
        ],
        [
          601,
          1420
        ],
        [
          613,
          1438
        ],
        [
          626,
          1451
        ],
        [
          636,
          1456
        ],
        [
          651,
          1471
        ],
        [
          675,
          1511
        ],
        [
          683,
          1528
        ],
        [
          686,
          1536
        ],
        [
          700,
          1573
        ],
        [
          705,
          1581
        ],
        [
          711,
          1596
        ],
        [
          715,
          1605
        ],
        [
          733,
          1633
        ],
        [
          741,
          1645
        ],
        [
          746,
          1656
        ],
        [
          755,
          1685
        ],
        [
          763,
          1695
        ],
        [
          775,
          1698
        ],
        [
          788,
          1698
        ],
        [
          796,
          1698
        ],
        [
          806,
          1696
        ],
        [
          816,
          1691
        ],
        [
          828,
          1685
        ],
        [
          838,
          1680
        ],
        [
          853,
          1671
        ],
        [
          863,
          1663
        ],
        [
          873,
          1658
        ],
        [
          883,
          1655
        ],
        [
          920,
          1641
        ],
        [
          945,
          1628
        ],
        [
          955,
          1621
        ],
        [
          963,
          1613
        ],
        [
          965,
          1588
        ],
        [
          943,
          1543
        ],
        [
          923,
          1510
        ],
        [
          921,
          1498
        ],
        [
          915,
          1481
        ],
        [
          903,
          1451
        ],
        [
          890,
          1418
        ],
        [
          871,
          1386
        ],
        [
          861,
          1365
        ],
        [
          855,
          1345
        ],
        [
          848,
          1333
        ],
        [
          830,
          1303
        ],
        [
          816,
          1271
        ],
        [
          810,
          1253
        ],
        [
          808,
          1243
        ],
        [
          801,
          1238
        ],
        [
          778,
          1215
        ],
        [
          763,
          1186
        ],
        [
          761,
          1170
        ],
        [
          756,
          1158
        ],
        [
          746,
          1141
        ]
      ],
      "completed_points": [
        [
          541,
          1256
        ],
        [
          746,
          1141
        ],
        [
          808,
          1243
        ],
        [
          890,
          1418
        ],
        [
          965,
          1588
        ],
        [
          963,
          1613
        ],
        [
          955,
          1621
        ],
        [
          945,
          1628
        ],
        [
          920,
          1641
        ],
        [
          806,
          1696
        ],
        [
          796,
          1698
        ],
        [
          775,
          1698
        ],
        [
          763,
          1695
        ],
        [
          755,
          1685
        ],
        [
          601,
          1420
        ],
        [
          551,
          1315
        ],
        [
          541,
          1270
        ]
      ],
      "points": [
        [
          541,
          1256
        ],
        [
          746,
          1141
        ],
        [
          808,
          1243
        ],
        [
          890,
          1418
        ],
        [
          965,
          1588
        ],
        [
          963,
          1613
        ],
        [
          955,
          1621
        ],
        [
          945,
          1628
        ],
        [
          920,
          1641
        ],
        [
          806,
          1696
        ],
        [
          796,
          1698
        ],
        [
          775,
          1698
        ],
        [
          763,
          1695
        ],
        [
          755,
          1685
        ],
        [
          601,
          1420
        ],
        [
          551,
          1315
        ],
        [
          541,
          1270
        ]
      ],
      "pixel_coordinates": [
        [
          541,
          1256
        ],
        [
          746,
          1141
        ],
        [
          808,
          1243
        ],
        [
          890,
          1418
        ],
        [
          965,
          1588
        ],
        [
          963,
          1613
        ],
        [
          955,
          1621
        ],
        [
          945,
          1628
        ],
        [
          920,
          1641
        ],
        [
          806,
          1696
        ],
        [
          796,
          1698
        ],
        [
          775,
          1698
        ],
        [
          763,
          1695
        ],
        [
          755,
          1685
        ],
        [
          601,
          1420
        ],
        [
          551,
          1315
        ],
        [
          541,
          1270
        ]
      ],
      "geographic_coordinates": [
        [
          4.512682819990376,
          7.516829714300741
        ],
        [
          4.512719402240376,
          7.51685019453574
        ],
        [
          4.5127304661403755,
          7.51683202945774
        ],
        [
          4.512745099040376,
          7.51680086388274
        ],
        [
          4.5127584827903755,
          7.51677058875274
        ],
        [
          4.512758125890375,
          7.516766136527741
        ],
        [
          4.512756698290375,
          7.516764711815741
        ],
        [
          4.512754913790376,
          7.51676346519274
        ],
        [
          4.512750452540375,
          7.51676115003574
        ],
        [
          4.512730109240375,
          7.51675135514074
        ],
        [
          4.512728324740376,
          7.51675099896274
        ],
        [
          4.512724577290376,
          7.51675099896274
        ],
        [
          4.5127224358903755,
          7.5167515332297405
        ],
        [
          4.5127210082903755,
          7.5167533141197405
        ],
        [
          4.512693526990375,
          7.51680050770474
        ],
        [
          4.512684604490375,
          7.516819207049741
        ],
        [
          4.512682819990376,
          7.51682722105474
        ]
      ],
      "center_lon": 4.512726109860963,
      "center_lat": 7.516784940630974
    },
    {
      "type": "polygon",
      "class": "commercial",
      "confidence": 1.0,
      "raw_points": [
        [
          325,
          1373
        ],
        [
          326,
          1385
        ],
        [
          335,
          1418
        ],
        [
          351,
          1455
        ],
        [
          370,
          1478
        ],
        [
          388,
          1511
        ],
        [
          390,
          1520
        ],
        [
          395,
          1561
        ],
        [
          403,
          1581
        ],
        [
          415,
          1601
        ],
        [
          423,
          1613
        ],
        [
          428,
          1620
        ],
        [
          435,
          1625
        ],
        [
          448,
          1648
        ],
        [
          448,
          1656
        ],
        [
          463,
          1685
        ],
        [
          468,
          1691
        ],
        [
          473,
          1700
        ],
        [
          495,
          1736
        ],
        [
          501,
          1746
        ],
        [
          510,
          1756
        ],
        [
          523,
          1780
        ],
        [
          528,
          1785
        ],
        [
          531,
          1791
        ],
        [
          541,
          1803
        ],
        [
          546,
          1810
        ],
        [
          555,
          1818
        ],
        [
          561,
          1820
        ],
        [
          568,
          1818
        ],
        [
          575,
          1815
        ],
        [
          595,
          1805
        ],
        [
          601,
          1801
        ],
        [
          613,
          1796
        ],
        [
          633,
          1788
        ],
        [
          651,
          1780
        ],
        [
          673,
          1770
        ],
        [
          675,
          1765
        ],
        [
          716,
          1750
        ],
        [
          728,
          1741
        ],
        [
          741,
          1735
        ],
        [
          745,
          1731
        ],
        [
          743,
          1713
        ],
        [
          721,
          1646
        ],
        [
          700,
          1618
        ],
        [
          691,
          1611
        ],
        [
          685,
          1590
        ],
        [
          665,
          1551
        ],
        [
          643,
          1508
        ],
        [
          628,
          1478
        ],
        [
          620,
          1468
        ],
        [
          615,
          1458
        ],
        [
          591,
          1418
        ],
        [
          581,
          1396
        ],
        [
          575,
          1383
        ],
        [
          573,
          1378
        ],
        [
          546,
          1325
        ],
        [
          533,
          1296
        ],
        [
          526,
          1281
        ],
        [
          525,
          1276
        ],
        [
          523,
          1271
        ],
        [
          520,
          1266
        ],
        [
          518,
          1261
        ]
      ],
      "processed_points": [
        [
          325,
          1373
        ],
        [
          326,
          1385
        ],
        [
          335,
          1418
        ],
        [
          351,
          1455
        ],
        [
          370,
          1478
        ],
        [
          388,
          1511
        ],
        [
          390,
          1520
        ],
        [
          395,
          1561
        ],
        [
          403,
          1581
        ],
        [
          415,
          1601
        ],
        [
          423,
          1613
        ],
        [
          428,
          1620
        ],
        [
          435,
          1625
        ],
        [
          448,
          1648
        ],
        [
          448,
          1656
        ],
        [
          463,
          1685
        ],
        [
          473,
          1700
        ],
        [
          495,
          1736
        ],
        [
          501,
          1746
        ],
        [
          510,
          1756
        ],
        [
          523,
          1780
        ],
        [
          531,
          1791
        ],
        [
          541,
          1803
        ],
        [
          546,
          1810
        ],
        [
          555,
          1818
        ],
        [
          568,
          1818
        ],
        [
          595,
          1805
        ],
        [
          613,
          1796
        ],
        [
          633,
          1788
        ],
        [
          651,
          1780
        ],
        [
          673,
          1770
        ],
        [
          716,
          1750
        ],
        [
          728,
          1741
        ],
        [
          741,
          1735
        ],
        [
          743,
          1713
        ],
        [
          721,
          1646
        ],
        [
          700,
          1618
        ],
        [
          691,
          1611
        ],
        [
          685,
          1590
        ],
        [
          665,
          1551
        ],
        [
          643,
          1508
        ],
        [
          628,
          1478
        ],
        [
          620,
          1468
        ],
        [
          615,
          1458
        ],
        [
          591,
          1418
        ],
        [
          581,
          1396
        ],
        [
          575,
          1383
        ],
        [
          546,
          1325
        ],
        [
          533,
          1296
        ],
        [
          526,
          1281
        ],
        [
          523,
          1271
        ],
        [
          518,
          1261
        ]
      ],
      "completed_points": [
        [
          325,
          1373
        ],
        [
          518,
          1261
        ],
        [
          721,
          1646
        ],
        [
          743,
          1713
        ],
        [
          741,
          1735
        ],
        [
          716,
          1750
        ],
        [
          673,
          1770
        ],
        [
          568,
          1818
        ],
        [
          555,
          1818
        ],
        [
          546,
          1810
        ],
        [
          531,
          1791
        ],
        [
          523,
          1780
        ],
        [
          501,
          1746
        ],
        [
          463,
          1685
        ],
        [
          403,
          1581
        ],
        [
          335,
          1418
        ],
        [
          326,
          1385
        ]
      ],
      "points": [
        [
          325,
          1373
        ],
        [
          518,
          1261
        ],
        [
          721,
          1646
        ],
        [
          743,
          1713
        ],
        [
          741,
          1735
        ],
        [
          716,
          1750
        ],
        [
          673,
          1770
        ],
        [
          568,
          1818
        ],
        [
          555,
          1818
        ],
        [
          546,
          1810
        ],
        [
          531,
          1791
        ],
        [
          523,
          1780
        ],
        [
          501,
          1746
        ],
        [
          463,
          1685
        ],
        [
          403,
          1581
        ],
        [
          335,
          1418
        ],
        [
          326,
          1385
        ]
      ],
      "pixel_coordinates": [
        [
          325,
          1373
        ],
        [
          518,
          1261
        ],
        [
          721,
          1646
        ],
        [
          743,
          1713
        ],
        [
          741,
          1735
        ],
        [
          716,
          1750
        ],
        [
          673,
          1770
        ],
        [
          568,
          1818
        ],
        [
          555,
          1818
        ],
        [
          546,
          1810
        ],
        [
          531,
          1791
        ],
        [
          523,
          1780
        ],
        [
          501,
          1746
        ],
        [
          463,
          1685
        ],
        [
          403,
          1581
        ],
        [
          335,
          1418
        ],
        [
          326,
          1385
        ]
      ],
      "geographic_coordinates": [
        [
          4.512644274790375,
          7.51680887788774
        ],
        [
          4.512678715640376,
          7.51682882385574
        ],
        [
          4.512714940990375,
          7.516760259590741
        ],
        [
          4.512718866890376,
          7.516748327627741
        ],
        [
          4.512718509990376,
          7.51674440966974
        ],
        [
          4.512714048740375,
          7.516741738334741
        ],
        [
          4.512706375390375,
          7.516738176554741
        ],
        [
          4.512687638140376,
          7.51672962828274
        ],
        [
          4.512685318290376,
          7.51672962828274
        ],
        [
          4.512683712240376,
          7.51673105299474
        ],
        [
          4.512681035490376,
          7.5167344366857405
        ],
        [
          4.512679607890376,
          7.516736395664741
        ],
        [
          4.512675681990376,
          7.5167424506907405
        ],
        [
          4.512668900890375,
          7.5167533141197405
        ],
        [
          4.512658193890376,
          7.5167718353757405
        ],
        [
          4.512646059290375,
          7.51680086388274
        ],
        [
          4.512644453240376,
          7.5168067408197405
        ]
      ],
      "center_lon": 4.512682725516846,
      "center_lat": 7.516759232960034
    },
    {
      "type": "polygon",
      "class": "commercial",
      "confidence": 1.0,
      "raw_points": [
        [
          778,
          1713
        ],
        [
          780,
          1726
        ],
        [
          791,
          1758
        ],
        [
          806,
          1790
        ],
        [
          816,
          1805
        ],
        [
          826,
          1823
        ],
        [
          836,
          1843
        ],
        [
          843,
          1856
        ],
        [
          851,
          1866
        ],
        [
          856,
          1876
        ],
        [
          860,
          1881
        ],
        [
          865,
          1886
        ],
        [
          886,
          1895
        ],
        [
          898,
          1896
        ],
        [
          911,
          1900
        ],
        [
          935,
          1901
        ],
        [
          946,
          1895
        ],
        [
          960,
          1883
        ],
        [
          970,
          1876
        ],
        [
          980,
          1870
        ],
        [
          991,
          1865
        ],
        [
          1005,
          1863
        ],
        [
          1021,
          1860
        ],
        [
          1041,
          1856
        ],
        [
          1056,
          1853
        ],
        [
          1065,
          1851
        ],
        [
          1075,
          1848
        ],
        [
          1081,
          1846
        ],
        [
          1086,
          1845
        ],
        [
          1088,
          1840
        ],
        [
          1070,
          1788
        ],
        [
          1045,
          1750
        ],
        [
          1035,
          1735
        ],
        [
          1025,
          1725
        ],
        [
          1011,
          1710
        ],
        [
          990,
          1673
        ],
        [
          976,
          1648
        ],
        [
          976,
          1638
        ],
        [
          973,
          1633
        ],
        [
          970,
          1628
        ],
        [
          965,
          1626
        ],
        [
          956,
          1626
        ],
        [
          941,
          1626
        ],
        [
          916,
          1631
        ],
        [
          910,
          1636
        ],
        [
          903,
          1638
        ],
        [
          861,
          1658
        ],
        [
          841,
          1666
        ],
        [
          823,
          1676
        ],
        [
          796,
          1700
        ],
        [
          791,
          1701
        ],
        [
          785,
          1705
        ],
        [
          781,
          1710
        ],
        [
          778,
          1716
        ]
      ],
      "processed_points": [
        [
          778,
          1713
        ],
        [
          780,
          1726
        ],
        [
          791,
          1758
        ],
        [
          806,
          1790
        ],
        [
          816,
          1805
        ],
        [
          826,
          1823
        ],
        [
          836,
          1843
        ],
        [
          843,
          1856
        ],
        [
          851,
          1866
        ],
        [
          856,
          1876
        ],
        [
          865,
          1886
        ],
        [
          886,
          1895
        ],
        [
          898,
          1896
        ],
        [
          911,
          1900
        ],
        [
          935,
          1901
        ],
        [
          946,
          1895
        ],
        [
          960,
          1883
        ],
        [
          970,
          1876
        ],
        [
          980,
          1870
        ],
        [
          991,
          1865
        ],
        [
          1005,
          1863
        ],
        [
          1021,
          1860
        ],
        [
          1041,
          1856
        ],
        [
          1056,
          1853
        ],
        [
          1065,
          1851
        ],
        [
          1075,
          1848
        ],
        [
          1086,
          1845
        ],
        [
          1070,
          1788
        ],
        [
          1045,
          1750
        ],
        [
          1035,
          1735
        ],
        [
          1025,
          1725
        ],
        [
          1011,
          1710
        ],
        [
          990,
          1673
        ],
        [
          976,
          1648
        ],
        [
          976,
          1638
        ],
        [
          970,
          1628
        ],
        [
          956,
          1626
        ],
        [
          941,
          1626
        ],
        [
          916,
          1631
        ],
        [
          903,
          1638
        ],
        [
          861,
          1658
        ],
        [
          841,
          1666
        ],
        [
          823,
          1676
        ],
        [
          796,
          1700
        ],
        [
          785,
          1705
        ]
      ],
      "completed_points": [
        [
          778,
          1713
        ],
        [
          780,
          1726
        ],
        [
          791,
          1758
        ],
        [
          806,
          1790
        ],
        [
          816,
          1805
        ],
        [
          826,
          1823
        ],
        [
          836,
          1843
        ],
        [
          843,
          1856
        ],
        [
          851,
          1866
        ],
        [
          856,
          1876
        ],
        [
          865,
          1886
        ],
        [
          886,
          1895
        ],
        [
          898,
          1896
        ],
        [
          911,
          1900
        ],
        [
          935,
          1901
        ],
        [
          946,
          1895
        ],
        [
          960,
          1883
        ],
        [
          970,
          1876
        ],
        [
          980,
          1870
        ],
        [
          991,
          1865
        ],
        [
          1005,
          1863
        ],
        [
          1021,
          1860
        ],
        [
          1041,
          1856
        ],
        [
          1056,
          1853
        ],
        [
          1065,
          1851
        ],
        [
          1075,
          1848
        ],
        [
          1086,
          1845
        ],
        [
          1070,
          1788
        ],
        [
          1045,
          1750
        ],
        [
          1035,
          1735
        ],
        [
          1025,
          1725
        ],
        [
          1011,
          1710
        ],
        [
          990,
          1673
        ],
        [
          976,
          1648
        ],
        [
          976,
          1638
        ],
        [
          970,
          1628
        ],
        [
          956,
          1626
        ],
        [
          941,
          1626
        ],
        [
          916,
          1631
        ],
        [
          903,
          1638
        ],
        [
          861,
          1658
        ],
        [
          841,
          1666
        ],
        [
          823,
          1676
        ],
        [
          796,
          1700
        ],
        [
          785,
          1705
        ],
        [
          778,
          1713
        ]
      ],
      "points": [
        [
          1070,
          1788
        ],
        [
          1086,
          1845
        ],
        [
          935,
          1901
        ],
        [
          911,
          1900
        ],
        [
          886,
          1895
        ],
        [
          865,
          1886
        ],
        [
          856,
          1876
        ],
        [
          843,
          1856
        ],
        [
          806,
          1790
        ],
        [
          791,
          1758
        ],
        [
          780,
          1726
        ],
        [
          778,
          1713
        ],
        [
          785,
          1705
        ],
        [
          823,
          1676
        ],
        [
          841,
          1666
        ],
        [
          916,
          1631
        ],
        [
          941,
          1626
        ],
        [
          956,
          1626
        ],
        [
          970,
          1628
        ]
      ],
      "pixel_coordinates": [
        [
          1070,
          1788
        ],
        [
          1086,
          1845
        ],
        [
          935,
          1901
        ],
        [
          911,
          1900
        ],
        [
          886,
          1895
        ],
        [
          865,
          1886
        ],
        [
          856,
          1876
        ],
        [
          843,
          1856
        ],
        [
          806,
          1790
        ],
        [
          791,
          1758
        ],
        [
          780,
          1726
        ],
        [
          778,
          1713
        ],
        [
          785,
          1705
        ],
        [
          823,
          1676
        ],
        [
          841,
          1666
        ],
        [
          916,
          1631
        ],
        [
          941,
          1626
        ],
        [
          956,
          1626
        ],
        [
          970,
          1628
        ]
      ],
      "geographic_coordinates": [
        [
          4.512777220040376,
          7.51673497095274
        ],
        [
          4.512780075240376,
          7.51672481987974
        ],
        [
          4.512753129290376,
          7.5167148468957405
        ],
        [
          4.512748846490376,
          7.51671502498474
        ],
        [
          4.512744385240375,
          7.5167159154297405
        ],
        [
          4.512740637790376,
          7.516717518230741
        ],
        [
          4.5127390317403755,
          7.516719299120741
        ],
        [
          4.512736711890375,
          7.516722860900741
        ],
        [
          4.512730109240375,
          7.51673461477474
        ],
        [
          4.512727432490376,
          7.516740313622741
        ],
        [
          4.512725469540376,
          7.51674601247074
        ],
        [
          4.512725112640376,
          7.516748327627741
        ],
        [
          4.512726361790375,
          7.516749752339741
        ],
        [
          4.512733142890376,
          7.516754916920741
        ],
        [
          4.512736354990375,
          7.516756697810741
        ],
        [
          4.512749738740376,
          7.51676293092574
        ],
        [
          4.5127541999903755,
          7.51676382137074
        ],
        [
          4.512756876740376,
          7.51676382137074
        ],
        [
          4.512759375040376,
          7.51676346519274
        ]
      ],
      "center_lon": 4.512744432200902,
      "center_lat": 7.516739470043267
    },
    {
      "type": "polygon",
      "class": "commercial",
      "confidence": 1.0,
      "raw_points": [
        [
          1010,
          1608
        ],
        [
          1026,
          1625
        ],
        [
          1043,
          1660
        ],
        [
          1053,
          1686
        ],
        [
          1058,
          1703
        ],
        [
          1076,
          1741
        ],
        [
          1095,
          1760
        ],
        [
          1098,
          1768
        ],
        [
          1108,
          1796
        ],
        [
          1115,
          1810
        ],
        [
          1123,
          1825
        ],
        [
          1128,
          1828
        ],
        [
          1140,
          1830
        ],
        [
          1150,
          1830
        ],
        [
          1168,
          1828
        ],
        [
          1190,
          1823
        ],
        [
          1216,
          1816
        ],
        [
          1243,
          1811
        ],
        [
          1268,
          1811
        ],
        [
          1310,
          1813
        ],
        [
          1323,
          1816
        ],
        [
          1330,
          1816
        ],
        [
          1336,
          1810
        ],
        [
          1343,
          1803
        ],
        [
          1343,
          1796
        ],
        [
          1343,
          1790
        ],
        [
          1338,
          1770
        ],
        [
          1330,
          1753
        ],
        [
          1321,
          1733
        ],
        [
          1310,
          1710
        ],
        [
          1300,
          1696
        ],
        [
          1280,
          1635
        ],
        [
          1271,
          1606
        ],
        [
          1263,
          1600
        ],
        [
          1238,
          1590
        ],
        [
          1231,
          1576
        ],
        [
          1223,
          1565
        ],
        [
          1216,
          1553
        ],
        [
          1216,
          1546
        ],
        [
          1216,
          1540
        ],
        [
          1213,
          1533
        ],
        [
          1208,
          1520
        ],
        [
          1203,
          1510
        ],
        [
          1203,
          1498
        ],
        [
          1198,
          1496
        ]
      ],
      "processed_points": [
        [
          1010,
          1608
        ],
        [
          1026,
          1625
        ],
        [
          1043,
          1660
        ],
        [
          1053,
          1686
        ],
        [
          1058,
          1703
        ],
        [
          1076,
          1741
        ],
        [
          1095,
          1760
        ],
        [
          1098,
          1768
        ],
        [
          1108,
          1796
        ],
        [
          1115,
          1810
        ],
        [
          1123,
          1825
        ],
        [
          1140,
          1830
        ],
        [
          1150,
          1830
        ],
        [
          1168,
          1828
        ],
        [
          1190,
          1823
        ],
        [
          1216,
          1816
        ],
        [
          1243,
          1811
        ],
        [
          1268,
          1811
        ],
        [
          1310,
          1813
        ],
        [
          1323,
          1816
        ],
        [
          1336,
          1810
        ],
        [
          1343,
          1803
        ],
        [
          1343,
          1790
        ],
        [
          1338,
          1770
        ],
        [
          1330,
          1753
        ],
        [
          1321,
          1733
        ],
        [
          1310,
          1710
        ],
        [
          1300,
          1696
        ],
        [
          1280,
          1635
        ],
        [
          1271,
          1606
        ],
        [
          1263,
          1600
        ],
        [
          1238,
          1590
        ],
        [
          1231,
          1576
        ],
        [
          1223,
          1565
        ],
        [
          1216,
          1553
        ],
        [
          1216,
          1540
        ],
        [
          1208,
          1520
        ],
        [
          1203,
          1510
        ],
        [
          1203,
          1498
        ]
      ],
      "completed_points": [
        [
          1010,
          1608
        ],
        [
          1203,
          1498
        ],
        [
          1271,
          1606
        ],
        [
          1338,
          1770
        ],
        [
          1343,
          1790
        ],
        [
          1343,
          1803
        ],
        [
          1336,
          1810
        ],
        [
          1323,
          1816
        ],
        [
          1150,
          1830
        ],
        [
          1140,
          1830
        ],
        [
          1123,
          1825
        ],
        [
          1076,
          1741
        ]
      ],
      "points": [
        [
          1010,
          1608
        ],
        [
          1203,
          1498
        ],
        [
          1271,
          1606
        ],
        [
          1338,
          1770
        ],
        [
          1343,
          1790
        ],
        [
          1343,
          1803
        ],
        [
          1336,
          1810
        ],
        [
          1323,
          1816
        ],
        [
          1150,
          1830
        ],
        [
          1140,
          1830
        ],
        [
          1123,
          1825
        ],
        [
          1076,
          1741
        ]
      ],
      "pixel_coordinates": [
        [
          1010,
          1608
        ],
        [
          1203,
          1498
        ],
        [
          1271,
          1606
        ],
        [
          1338,
          1770
        ],
        [
          1343,
          1790
        ],
        [
          1343,
          1803
        ],
        [
          1336,
          1810
        ],
        [
          1323,
          1816
        ],
        [
          1150,
          1830
        ],
        [
          1140,
          1830
        ],
        [
          1123,
          1825
        ],
        [
          1076,
          1741
        ]
      ],
      "geographic_coordinates": [
        [
          4.512766513040376,
          7.51676702697274
        ],
        [
          4.512800953890376,
          7.51678661676274
        ],
        [
          4.512813088490375,
          7.51676738315074
        ],
        [
          4.512825044640375,
          7.516738176554741
        ],
        [
          4.512825936890375,
          7.51673461477474
        ],
        [
          4.512825936890375,
          7.516732299617741
        ],
        [
          4.512824687740376,
          7.51673105299474
        ],
        [
          4.512822367890376,
          7.51672998446074
        ],
        [
          4.512791496040376,
          7.51672749121474
        ],
        [
          4.512789711540376,
          7.51672749121474
        ],
        [
          4.512786677890376,
          7.516728381659741
        ],
        [
          4.512778290740376,
          7.51674334113574
        ]
      ],
      "center_lon": 4.51280422547371,
      "center_lat": 7.516742821709491
    },
    {
      "type": "polygon",
      "class": "commercial",
      "confidence": 1.0,
      "raw_points": [
        [
          1223,
          1483
        ],
        [
          1226,
          1493
        ],
        [
          1250,
          1570
        ],
        [
          1285,
          1631
        ],
        [
          1303,
          1656
        ],
        [
          1303,
          1663
        ],
        [
          1316,
          1676
        ],
        [
          1323,
          1685
        ],
        [
          1333,
          1693
        ],
        [
          1343,
          1703
        ],
        [
          1348,
          1711
        ],
        [
          1363,
          1743
        ],
        [
          1363,
          1750
        ],
        [
          1366,
          1758
        ],
        [
          1386,
          1783
        ],
        [
          1401,
          1796
        ],
        [
          1411,
          1800
        ],
        [
          1423,
          1800
        ],
        [
          1436,
          1796
        ],
        [
          1463,
          1781
        ],
        [
          1495,
          1770
        ],
        [
          1503,
          1768
        ],
        [
          1510,
          1768
        ],
        [
          1581,
          1771
        ],
        [
          1610,
          1773
        ],
        [
          1618,
          1773
        ],
        [
          1621,
          1768
        ],
        [
          1621,
          1758
        ],
        [
          1621,
          1733
        ],
        [
          1611,
          1698
        ],
        [
          1586,
          1665
        ],
        [
          1560,
          1608
        ],
        [
          1660,
          1790
        ],
        [
          1653,
          1770
        ],
        [
          1636,
          1721
        ],
        [
          1623,
          1691
        ],
        [
          1616,
          1680
        ],
        [
          1596,
          1658
        ],
        [
          1570,
          1628
        ],
        [
          1546,
          1583
        ],
        [
          1545,
          1576
        ],
        [
          1543,
          1571
        ],
        [
          1510,
          1526
        ],
        [
          1485,
          1478
        ],
        [
          1473,
          1465
        ],
        [
          1463,
          1450
        ],
        [
          1455,
          1435
        ],
        [
          1450,
          1423
        ],
        [
          1450,
          1416
        ],
        [
          1450,
          1406
        ],
        [
          1448,
          1401
        ]
      ],
      "processed_points": [
        [
          1223,
          1483
        ],
        [
          1226,
          1493
        ],
        [
          1250,
          1570
        ],
        [
          1285,
          1631
        ],
        [
          1303,
          1656
        ],
        [
          1316,
          1676
        ],
        [
          1323,
          1685
        ],
        [
          1333,
          1693
        ],
        [
          1343,
          1703
        ],
        [
          1348,
          1711
        ],
        [
          1363,
          1743
        ],
        [
          1366,
          1758
        ],
        [
          1386,
          1783
        ],
        [
          1401,
          1796
        ],
        [
          1411,
          1800
        ],
        [
          1423,
          1800
        ],
        [
          1436,
          1796
        ],
        [
          1463,
          1781
        ],
        [
          1495,
          1770
        ],
        [
          1503,
          1768
        ],
        [
          1581,
          1771
        ],
        [
          1610,
          1773
        ],
        [
          1618,
          1773
        ],
        [
          1621,
          1758
        ],
        [
          1621,
          1733
        ],
        [
          1611,
          1698
        ],
        [
          1586,
          1665
        ],
        [
          1560,
          1608
        ],
        [
          1660,
          1790
        ],
        [
          1653,
          1770
        ],
        [
          1636,
          1721
        ],
        [
          1623,
          1691
        ],
        [
          1616,
          1680
        ],
        [
          1596,
          1658
        ],
        [
          1570,
          1628
        ],
        [
          1546,
          1583
        ],
        [
          1543,
          1571
        ],
        [
          1510,
          1526
        ],
        [
          1485,
          1478
        ],
        [
          1473,
          1465
        ],
        [
          1463,
          1450
        ],
        [
          1455,
          1435
        ],
        [
          1450,
          1423
        ],
        [
          1450,
          1406
        ]
      ],
      "completed_points": [
        [
          1223,
          1483
        ],
        [
          1450,
          1406
        ],
        [
          1623,
          1691
        ],
        [
          1636,
          1721
        ],
        [
          1660,
          1790
        ],
        [
          1423,
          1800
        ],
        [
          1411,
          1800
        ],
        [
          1401,
          1796
        ],
        [
          1386,
          1783
        ],
        [
          1366,
          1758
        ],
        [
          1285,
          1631
        ],
        [
          1250,
          1570
        ],
        [
          1226,
          1493
        ]
      ],
      "points": [
        [
          1223,
          1483
        ],
        [
          1450,
          1406
        ],
        [
          1623,
          1691
        ],
        [
          1636,
          1721
        ],
        [
          1660,
          1790
        ],
        [
          1423,
          1800
        ],
        [
          1411,
          1800
        ],
        [
          1401,
          1796
        ],
        [
          1386,
          1783
        ],
        [
          1366,
          1758
        ],
        [
          1285,
          1631
        ],
        [
          1250,
          1570
        ],
        [
          1226,
          1493
        ]
      ],
      "pixel_coordinates": [
        [
          1223,
          1483
        ],
        [
          1450,
          1406
        ],
        [
          1623,
          1691
        ],
        [
          1636,
          1721
        ],
        [
          1660,
          1790
        ],
        [
          1423,
          1800
        ],
        [
          1411,
          1800
        ],
        [
          1401,
          1796
        ],
        [
          1386,
          1783
        ],
        [
          1366,
          1758
        ],
        [
          1285,
          1631
        ],
        [
          1250,
          1570
        ],
        [
          1226,
          1493
        ]
      ],
      "geographic_coordinates": [
        [
          4.5128045228903755,
          7.5167892880977405
        ],
        [
          4.512845031040376,
          7.51680300095074
        ],
        [
          4.512875902890376,
          7.5167522455857405
        ],
        [
          4.512878222740375,
          7.516746902915741
        ],
        [
          4.512882505540376,
          7.51673461477474
        ],
        [
          4.512840212890375,
          7.51673283388474
        ],
        [
          4.512838071490376,
          7.51673283388474
        ],
        [
          4.5128362869903755,
          7.51673354624074
        ],
        [
          4.512833610240375,
          7.51673586139774
        ],
        [
          4.512830041240376,
          7.516740313622741
        ],
        [
          4.512815586790375,
          7.51676293092574
        ],
        [
          4.512809341040375,
          7.516773794354741
        ],
        [
          4.512805058240375,
          7.516787507207741
        ]
      ],
      "center_lon": 4.512838030309606,
      "center_lat": 7.516755821064892
    }
  ],
  "crs": "EPSG:4326",
  "transform": [
    1.7845000000002736e-07,
    0.0,
    4.512586189315376,
    0.0,
    -1.78088999999971e-07,
    7.51705348312924,
    0.0,
    0.0,
    1.0
  ],
  "bounds": [
    4.512586189315376,
    7.5162333832842405,
    4.513277504615376,
    7.51705348312924
  ],
  "resolution_info": {
    "pixel_size_x_meters": 1.7845000000002736e-07,
    "pixel_size_y_meters": 1.78088999999971e-07,
    "pixel_size_x_cm": 1.7845000000002737e-05,
    "pixel_size_y_cm": 1.7808899999997098e-05,
    "ground_sample_distance": 1.7845000000002736e-07
  }
}